[
  {
    "_id": {
      "$oid": "6090d81eb9cda016f315b3ad"
    },
    "FileName": "ex_ndy3.dat",
    "BriefInfo": "",
    "Size": "4.93KB",
    "Description": "",
    "Source": "",
    "Label": "No",
    "Number_of_Attribute": 5,
    "Number_of_Instance": 96,
    "Keywords": [],
    "AttrInfo": [
      {
        "attrName": "",
        "attrDescription": ""
      }
    ],
    "UserName": "123456@qq.com"
  },
  {
    "_id": {
      "$oid": "6090d81eb9cda016f315b3ac"
    },
    "FileName": "ex_ndy2.dat",
    "BriefInfo": "",
    "Size": "4.93KB",
    "Description": "",
    "Source": "",
    "Label": "No",
    "Number_of_Attribute": 5,
    "Number_of_Instance": 96,
    "Keywords": [],
    "AttrInfo": [
      {
        "attrName": "",
        "attrDescription": ""
      }
    ],
    "UserName": "123456@qq.com"
  },
  {
    "_id": {
      "$oid": "6090d81db9cda016f315b3ab"
    },
    "FileName": "ex_ndy.dat",
    "BriefInfo": "",
    "Size": "4.93KB",
    "Description": "",
    "Source": "",
    "Label": "No",
    "Number_of_Attribute": 5,
    "Number_of_Instance": 96,
    "Keywords": [],
    "AttrInfo": [
      {
        "attrName": "",
        "attrDescription": ""
      }
    ],
    "UserName": "123456@qq.com"
  }
]